pipdeptree/__init__.py
pipdeptree/__main__.py
pipdeptree/_adapter.py
pipdeptree/_cli.py
pipdeptree/_discovery.py
pipdeptree/_validate.py
pipdeptree/py.typed
pipdeptree/version.py
pipdeptree/_models/__init__.py
pipdeptree/_models/dag.py
pipdeptree/_models/package.py
pipdeptree/_render/__init__.py
pipdeptree/_render/graphviz.py
pipdeptree/_render/json.py
pipdeptree/_render/json_tree.py
pipdeptree/_render/mermaid.py
pipdeptree/_render/text.py
pipdeptree-2.18.0.dist-info/METADATA
pipdeptree-2.18.0.dist-info/WHEEL
pipdeptree-2.18.0.dist-info/entry_points.txt
pipdeptree-2.18.0.dist-info/licenses/LICENSE
pipdeptree-2.18.0.dist-info/RECORD
