Metadata-Version: 2.3
Name: pipdeptree
Version: 2.18.0
Summary: Command line utility to show dependency tree of packages.
Project-URL: Changelog, https://github.com/tox-dev/pipdeptree/blob/main/CHANGES.md
Project-URL: Documentation, https://github.com/tox-dev/pipdeptree/blob/main/README.md#pipdeptree
Project-URL: Homepage, https://github.com/tox-dev/pipdeptree
Project-URL: Source, https://github.com/tox-dev/pipdeptree
Project-URL: Tracker, https://github.com/tox-dev/pipdeptree/issues
Maintainer-email: Bernát Gábor <gaborjbernat@gmail.com>, Vineet Naik <naikvin@gmail.com>
License: Copyright (c) The pipdeptree developers
License-File: LICENSE
Keywords: application,cache,directory,log,user
Classifier: Development Status :: 5 - Production/Stable
Classifier: Environment :: Console
Classifier: Intended Audience :: Developers
Classifier: License :: OSI Approved :: MIT License
Classifier: Operating System :: OS Independent
Classifier: Programming Language :: Python
Classifier: Programming Language :: Python :: 3 :: Only
Classifier: Programming Language :: Python :: 3.8
Classifier: Programming Language :: Python :: 3.9
Classifier: Programming Language :: Python :: 3.10
Classifier: Programming Language :: Python :: 3.11
Classifier: Programming Language :: Python :: 3.12
Requires-Python: >=3.8
Requires-Dist: packaging>=23.1
Requires-Dist: pip>=23.1.2
Provides-Extra: graphviz
Requires-Dist: graphviz>=0.20.1; extra == 'graphviz'
Provides-Extra: test
Requires-Dist: covdefaults>=2.3; extra == 'test'
Requires-Dist: diff-cover>=8.0.1; extra == 'test'
Requires-Dist: pytest-cov>=4.1; extra == 'test'
Requires-Dist: pytest-mock>=3.12; extra == 'test'
Requires-Dist: pytest>=7.4.3; extra == 'test'
Requires-Dist: virtualenv<21,>=20.25; extra == 'test'
